{
  "Workflows": [
    {
      "Path": null,
      "SortBy": 0,
      "VariablesSectionElementsOrder": [],
      "ArgumentsSectionElementsOrder": null,
      "ConstantsSectionElementsOrder": [],
      "AddedNamespaces": null
    },
    {
      "Path": "Main.xaml",
      "SortBy": 0,
      "VariablesSectionElementsOrder": [
        "DT&Sequence_2",
        "Values&Sequence_3"
      ],
      "ArgumentsSectionElementsOrder": [],
      "ConstantsSectionElementsOrder": [],
      "AddedNamespaces": null
    },
    {
      "Path": "Sequence.xaml",
      "SortBy": 0,
      "VariablesSectionElementsOrder": [
        "DT&Sequence_2",
        "index&Sequence_2"
      ],
      "ArgumentsSectionElementsOrder": [],
      "ConstantsSectionElementsOrder": [],
      "AddedNamespaces": null
    },
    {
      "Path": "Sequence1.xaml",
      "SortBy": 0,
      "VariablesSectionElementsOrder": [
        "DT1&Sequence_1",
        "DT2&Sequence_1",
        "ResultDT&Sequence_1",
        "rowindexDT1&Sequence_1",
        "rowindexDT2&Sequence_1"
      ],
      "ArgumentsSectionElementsOrder": [],
      "ConstantsSectionElementsOrder": [],
      "AddedNamespaces": null
    },
    {
      "Path": "Sequence2.xaml",
      "SortBy": 0,
      "VariablesSectionElementsOrder": [
        "NewJoinerDT&Sequence_2",
        "MasterDT&Sequence_2",
        "ResultDT&Sequence_2",
        "rowIndx&Sequence_3",
        "columns&Sequence_3"
      ],
      "ArgumentsSectionElementsOrder": [],
      "ConstantsSectionElementsOrder": [],
      "AddedNamespaces": null
    },
    {
      "Path": "Sequence3.xaml",
      "SortBy": 0,
      "VariablesSectionElementsOrder": [
        "columns&Sequence_1",
        "Rows&Sequence_1"
      ],
      "ArgumentsSectionElementsOrder": [],
      "ConstantsSectionElementsOrder": [],
      "AddedNamespaces": null
    }
  ]
}